README.rst
setup.py
futurefinity/__init__.py
futurefinity/client.py
futurefinity/protocol.py
futurefinity/routing.py
futurefinity/security.py
futurefinity/server.py
futurefinity/template.py
futurefinity/utils.py
futurefinity/web.py
futurefinity.egg-info/.DS_Store
futurefinity.egg-info/PKG-INFO
futurefinity.egg-info/SOURCES.txt
futurefinity.egg-info/dependency_links.txt
futurefinity.egg-info/not-zip-safe
futurefinity.egg-info/requires.txt
futurefinity.egg-info/top_level.txt