Metadata-Version: 1.1
Name: futurefinity
Version: 0.2.1
Summary: FutureFinity is an asynchronous Python web framework designed for asyncio and native coroutines.
Home-page: https://github.com/futursolo/futurefinity
Author: Futur Solo
Author-email: futursolo@gmail.com
License: Apache License 2.0
Platform: UNKNOWN
Classifier: License :: OSI Approved :: Apache Software License
Classifier: Operating System :: MacOS
Classifier: Operating System :: MacOS :: MacOS X
Classifier: Operating System :: Microsoft
Classifier: Operating System :: Microsoft :: Windows
Classifier: Operating System :: POSIX
Classifier: Operating System :: POSIX :: Linux
Classifier: Operating System :: Unix
Classifier: Programming Language :: Python
Classifier: Programming Language :: Python :: 3 :: Only
Classifier: Programming Language :: Python :: Implementation :: CPython
